Products.CMFCore-3.7-py3.9-nspkg.pth
Products/CMFCore/ActionInformation.py
Products/CMFCore/ActionProviderBase.py
Products/CMFCore/ActionsTool.py
Products/CMFCore/CMFBTreeFolder.py
Products/CMFCore/CMFCatalogAware.py
Products/CMFCore/CachingPolicyManager.py
Products/CMFCore/CatalogTool.py
Products/CMFCore/ContentTypeRegistry.py
Products/CMFCore/CookieCrumbler.py
Products/CMFCore/DirectoryView.py
Products/CMFCore/DiscussionTool.py
Products/CMFCore/DynamicType.py
Products/CMFCore/Expression.py
Products/CMFCore/FSDTMLMethod.py
Products/CMFCore/FSFile.py
Products/CMFCore/FSImage.py
Products/CMFCore/FSMetadata.py
Products/CMFCore/FSObject.py
Products/CMFCore/FSPageTemplate.py
Products/CMFCore/FSPropertiesObject.py
Products/CMFCore/FSPythonScript.py
Products/CMFCore/FSReSTMethod.py
Products/CMFCore/FSSTXMethod.py
Products/CMFCore/FSZSQLMethod.py
Products/CMFCore/MemberDataTool.py
Products/CMFCore/MembershipTool.py
Products/CMFCore/PortalContent.py
Products/CMFCore/PortalFolder.py
Products/CMFCore/PortalObject.py
Products/CMFCore/RegistrationTool.py
Products/CMFCore/Skinnable.py
Products/CMFCore/SkinsContainer.py
Products/CMFCore/SkinsTool.py
Products/CMFCore/TypesTool.py
Products/CMFCore/URLTool.py
Products/CMFCore/UndoTool.py
Products/CMFCore/WorkflowCore.py
Products/CMFCore/WorkflowTool.py
Products/CMFCore/__init__.py
Products/CMFCore/configure.zcml
Products/CMFCore/content.zcml
Products/CMFCore/event.zcml
Products/CMFCore/exceptions.py
Products/CMFCore/explicitacquisition.py
Products/CMFCore/indexing.py
Products/CMFCore/meta.zcml
Products/CMFCore/namespace.py
Products/CMFCore/overrides.zcml
Products/CMFCore/permissions.py
Products/CMFCore/permissions.zcml
Products/CMFCore/subscribers.py
Products/CMFCore/subscribers.zcml
Products/CMFCore/testing.py
Products/CMFCore/testing.zcml
Products/CMFCore/tool.gif
Products/CMFCore/tool.zcml
Products/CMFCore/utils.py
Products/CMFCore/zcml.py
Products/CMFCore/Extensions/TestRecord.py
Products/CMFCore/browser/__init__.py
Products.CMFCore-3.7.dist-info/LICENSE.txt
Products.CMFCore-3.7.dist-info/METADATA
Products.CMFCore-3.7.dist-info/WHEEL
Products.CMFCore-3.7.dist-info/entry_points.txt
Products.CMFCore-3.7.dist-info/namespace_packages.txt
Products.CMFCore-3.7.dist-info/top_level.txt
Products.CMFCore-3.7.dist-info/RECORD
