Metadata-Version: 2.1
Name: Products.CMFCore
Version: 3.7
Summary: Zope Content Management Framework core components
Home-page: https://github.com/zopefoundation/Products.CMFCore
Author: Zope Foundation and Contributors
Author-email: zope-cmf@zope.org
License: ZPL-2.1
Project-URL: Documentation, https://zope.readthedocs.io
Project-URL: Issue Tracker, https://github.com/zopefoundation/Products.CMFCore/issues
Project-URL: Sources, https://github.com/zopefoundation/Products.CMFCore
Keywords: web application server zope cmf
Classifier: Development Status :: 5 - Production/Stable
Classifier: Framework :: Plone
Classifier: Framework :: Zope :: 5
Classifier: Intended Audience :: Developers
Classifier: License :: OSI Approved :: Zope Public License
Classifier: Programming Language :: Python :: 3
Classifier: Programming Language :: Python :: 3.9
Classifier: Programming Language :: Python :: 3.10
Classifier: Programming Language :: Python :: 3.11
Classifier: Programming Language :: Python :: 3.12
Classifier: Programming Language :: Python :: 3.13
Classifier: Programming Language :: Python :: Implementation :: CPython
Classifier: Topic :: Software Development :: Libraries :: Application Frameworks
Requires-Python: >=3.9
License-File: LICENSE.txt
Requires-Dist: setuptools
Requires-Dist: Zope>=5
Requires-Dist: docutils>0.15
Requires-Dist: five.localsitemanager
Requires-Dist: Products.BTreeFolder2
Requires-Dist: Products.GenericSetup>=2.1.2
Requires-Dist: Products.MailHost>=4.0
Requires-Dist: Products.PythonScripts
Requires-Dist: Products.StandardCacheManagers
Requires-Dist: Products.ZCatalog>=4.0a2
Requires-Dist: zope.datetime
Requires-Dist: zope.interface>=3.8
Provides-Extra: test
Requires-Dist: Products.StandardCacheManagers; extra == "test"
Provides-Extra: zsql
Requires-Dist: Products.ZSQLMethods>=3.0.0b1; extra == "zsql"
Provides-Extra: docs
Requires-Dist: Sphinx; extra == "docs"
Requires-Dist: repoze.sphinx.autointerface; extra == "docs"
Requires-Dist: pkginfo; extra == "docs"
